class_based_auth_views/__init__.py
class_based_auth_views/utils.py
class_based_auth_views/views.py
django_class_based_auth_views-0.4.dist-info/DESCRIPTION.rst
django_class_based_auth_views-0.4.dist-info/METADATA
django_class_based_auth_views-0.4.dist-info/RECORD
django_class_based_auth_views-0.4.dist-info/WHEEL
django_class_based_auth_views-0.4.dist-info/metadata.json
django_class_based_auth_views-0.4.dist-info/top_level.txt
